pybritive/__init__.py
pybritive/britive_cli.py
pybritive/cli_interface.py
pybritive/choices/__init__.py
pybritive/choices/backend.py
pybritive/choices/browser.py
pybritive/choices/mode.py
pybritive/choices/output_format.py
pybritive/choices/profile_type.py
pybritive/choices/ssh_key_source.py
pybritive/choices/ssh_push_public_key.py
pybritive/commands/__init__.py
pybritive/commands/api.py
pybritive/commands/aws.py
pybritive/commands/cache.py
pybritive/commands/checkin.py
pybritive/commands/checkout.py
pybritive/commands/clear.py
pybritive/commands/configure.py
pybritive/commands/login.py
pybritive/commands/logout.py
pybritive/commands/ls.py
pybritive/commands/request.py
pybritive/commands/secret.py
pybritive/commands/ssh.py
pybritive/commands/user.py
pybritive/completers/__init__.py
pybritive/completers/api.py
pybritive/completers/api_command.py
pybritive/completers/bash_gte_42.py
pybritive/completers/powershell_completion.py
pybritive/completers/profile.py
pybritive/helpers/__init__.py
pybritive/helpers/api_method_argument_decorator.py
pybritive/helpers/aws_credential_process.py
pybritive/helpers/build_britive.py
pybritive/helpers/cache.py
pybritive/helpers/cloud_credential_printer.py
pybritive/helpers/config.py
pybritive/helpers/credentials.py
pybritive/helpers/encryption.py
pybritive/helpers/k8s_exec.py
pybritive/helpers/k8s_exec_credential_builder.py
pybritive/helpers/kube_config_builder.py
pybritive/helpers/profile_argument_decorator.py
pybritive/helpers/split.py
pybritive/options/__init__.py
pybritive/options/alias.py
pybritive/options/aws_console_duration.py
pybritive/options/aws_credentials_file.py
pybritive/options/aws_profile.py
pybritive/options/blocktime.py
pybritive/options/britive_options.py
pybritive/options/browser.py
pybritive/options/checked_out.py
pybritive/options/configure_alias.py
pybritive/options/configure_backend.py
pybritive/options/configure_prompt.py
pybritive/options/configure_tenant.py
pybritive/options/console.py
pybritive-2.3.1.dist-info/licenses/LICENSE
pybritive-2.3.1.dist-info/METADATA
pybritive-2.3.1.dist-info/WHEEL
pybritive-2.3.1.dist-info/entry_points.txt
pybritive-2.3.1.dist-info/top_level.txt
pybritive-2.3.1.dist-info/RECORD
