Metadata-Version: 2.4
Name: pybritive
Version: 2.3.1
Summary: A pure Python CLI for Britive
Author-email: "Britive Inc." <support@britive.com>
License: MIT License
Project-URL: Homepage, https://www.britive.com
Project-URL: Documentation, https://britive.github.io/python-cli/
Project-URL: Repository, https://github.com/britive/python-cli.git
Project-URL: Issues, https://github.com/britive/python-cli/issues
Project-URL: Changelog, https://github.com/britive/python-cli/blob/main/CHANGELOG.md
Keywords: britive,cpam,identity,jit,cli
Classifier: License :: OSI Approved :: MIT License
Classifier: Operating System :: OS Independent
Classifier: Programming Language :: Python
Classifier: Programming Language :: Python :: 3.9
Classifier: Programming Language :: Python :: 3.10
Classifier: Programming Language :: Python :: 3.11
Classifier: Programming Language :: Python :: 3.12
Classifier: Programming Language :: Python :: 3.13
Classifier: Topic :: Internet
Classifier: Topic :: Security
Classifier: Topic :: Utilities
Requires-Python: >=3.9
License-File: LICENSE
Requires-Dist: britive<5.0,>=4.1.2
Requires-Dist: click>=8.1.7
Requires-Dist: colored>=2.2.5
Requires-Dist: cryptography
Requires-Dist: jmespath
Requires-Dist: merge-args
Requires-Dist: pyjwt
Requires-Dist: python-dateutil
Requires-Dist: PyYAML
Requires-Dist: requests>=2.31.0
Requires-Dist: tabulate
Requires-Dist: toml
Provides-Extra: openshift
Requires-Dist: beautifulsoup4; extra == "openshift"
Provides-Extra: aws
Requires-Dist: boto3; extra == "aws"
Dynamic: license-file
